<!DOCTYPE PATCH  SYSTEM "http://vvvv.org/versions/vvvv45beta29.2.dtd" >
   <PATCH nodename="C:\Users\julian\Dropbox\__FH\Bachelor\Entwicklung\MarysGun\Patches\subpatches\sound.v4p" systemname="sound" filename="C:\Users\julian\Dropbox\__FH\Bachelor\Entwicklung\patches\marys gun\subpatches\sound.v4p">
   <BOUNDS type="Window" left="0" top="0" width="18825" height="18180">
   </BOUNDS>
   <NODE componentmode="InABox" id="32" nodename="IOBox (String)" systemname="IOBox (String)">
   <BOUNDS height="0" left="11490" top="13170" type="Node" width="0">
   </BOUNDS>
   <BOUNDS height="160" left="9480" top="5625" type="Window" width="215">
   </BOUNDS>
   <BOUNDS height="240" left="11490" top="13170" type="Box" width="6105">
   </BOUNDS>
   <PIN pinname="Output String" visible="1">
   </PIN>
   <PIN pinname="Input String" visible="1">
   </PIN>
   <PIN pinname="Descriptive Name" slicecount="1" encoded="0" values="|File Name|">
   </PIN>
   </NODE>
   <NODE nodename="IOBox (String)" componentmode="InABox" id="20" systemname="IOBox (String)" exposed="1">
   <BOUNDS type="Node" left="11595" top="16200" width="3765" height="270">
   </BOUNDS>
   <BOUNDS type="Box" left="11595" top="16200" width="3765" height="270">
   </BOUNDS>
   <PIN pinname="Input String" visible="0" slicecount="1" encoded="0" values="|I:\AUDIO\Samples\VGEE\VEE Effects\VEE FX 036.wav|">
   </PIN>
   <PIN pinname="Output String" visible="1">
   </PIN>
   <PIN pinname="Show Grid" slicecount="1" values="0">
   </PIN>
   <PIN pinname="String Type" slicecount="1" values="MultiLine">
   </PIN>
   </NODE>
   <NODE nodename="IOBox (String)" componentmode="InABox" id="19" systemname="IOBox (String)" exposed="1">
   <BOUNDS type="Node" left="11595" top="16530" width="3765" height="270">
   </BOUNDS>
   <BOUNDS type="Box" left="11595" top="16530" width="3765" height="270">
   </BOUNDS>
   <PIN pinname="Input String" visible="0" slicecount="1" encoded="0" values="|I:\AUDIO\Samples\VGEE\VEE Effects\VEE FX 039.wav|">
   </PIN>
   <PIN pinname="Output String" visible="1">
   </PIN>
   <PIN pinname="Show Grid" slicecount="1" values="0">
   </PIN>
   <PIN pinname="String Type" slicecount="1" values="MultiLine">
   </PIN>
   </NODE>
   <NODE nodename="IOBox (String)" componentmode="InABox" id="18" systemname="IOBox (String)" exposed="1">
   <BOUNDS type="Node" left="11295" top="16875" width="3765" height="270">
   </BOUNDS>
   <BOUNDS type="Box" left="11295" top="16875" width="3765" height="270">
   </BOUNDS>
   <PIN pinname="Input String" visible="0" slicecount="1" encoded="0" values="|I:\AUDIO\Samples\VGEE\VEE Effects\VEE FX 048.wav|">
   </PIN>
   <PIN pinname="Output String" visible="1">
   </PIN>
   <PIN pinname="Show Grid" slicecount="1" values="0">
   </PIN>
   <PIN pinname="String Type" slicecount="1" values="MultiLine">
   </PIN>
   </NODE>
   <NODE nodename="IOBox (String)" componentmode="InABox" id="17" systemname="IOBox (String)" exposed="1">
   <BOUNDS type="Node" left="11595" top="17235" width="3765" height="270">
   </BOUNDS>
   <BOUNDS type="Box" left="11595" top="17235" width="3765" height="270">
   </BOUNDS>
   <PIN pinname="Input String" visible="0" slicecount="1" encoded="0" values="|I:\AUDIO\Samples\VGEE\VEE Effects\VEE FX 049.wav|">
   </PIN>
   <PIN pinname="Output String" visible="1">
   </PIN>
   <PIN pinname="Show Grid" slicecount="1" values="0">
   </PIN>
   <PIN pinname="String Type" slicecount="1" values="MultiLine">
   </PIN>
   </NODE>
   <NODE nodename="IOBox (String)" componentmode="InABox" id="16" systemname="IOBox (String)" exposed="1">
   <BOUNDS type="Node" left="11595" top="17580" width="3765" height="270">
   </BOUNDS>
   <BOUNDS type="Box" left="11595" top="17580" width="3765" height="270">
   </BOUNDS>
   <PIN pinname="Input String" visible="0" slicecount="1" encoded="0" values="|I:\AUDIO\Samples\VGEE\VEE Effects\VEE FX 056.wav|">
   </PIN>
   <PIN pinname="Output String" visible="1">
   </PIN>
   <PIN pinname="Show Grid" slicecount="1" values="0">
   </PIN>
   <PIN pinname="String Type" slicecount="1" values="MultiLine">
   </PIN>
   </NODE>
   <NODE nodename="IOBox (String)" componentmode="InABox" id="15" systemname="IOBox (String)">
   <BOUNDS type="Node" left="11595" top="17925" width="3765" height="270">
   </BOUNDS>
   <BOUNDS type="Box" left="11595" top="17925" width="3765" height="270">
   </BOUNDS>
   <PIN pinname="Input String" visible="0" slicecount="1" encoded="0" values="|I:\AUDIO\Samples\VGEE\VEE Effects\VEE FX 057.wav|">
   </PIN>
   <PIN pinname="Output String" visible="1">
   </PIN>
   <PIN pinname="Show Grid" slicecount="1" values="0">
   </PIN>
   <PIN pinname="String Type" slicecount="1" values="MultiLine">
   </PIN>
   </NODE>
   <NODE nodename="IOBox (String)" componentmode="InABox" id="14" systemname="IOBox (String)">
   <BOUNDS type="Node" left="15705" top="16155" width="3765" height="270">
   </BOUNDS>
   <BOUNDS type="Box" left="15705" top="16155" width="3765" height="270">
   </BOUNDS>
   <PIN pinname="Input String" visible="0" slicecount="1" encoded="0" values="|I:\AUDIO\Samples\VGEE\VEE Effects\VEE FX 064.wav|">
   </PIN>
   <PIN pinname="Output String" visible="1">
   </PIN>
   <PIN pinname="Show Grid" slicecount="1" values="0">
   </PIN>
   <PIN pinname="String Type" slicecount="1" values="MultiLine">
   </PIN>
   </NODE>
   <NODE nodename="IOBox (String)" componentmode="InABox" id="13" systemname="IOBox (String)">
   <BOUNDS type="Node" left="15705" top="15765" width="600" height="270">
   </BOUNDS>
   <BOUNDS type="Box" left="15705" top="15765" width="1125" height="360">
   </BOUNDS>
   <PIN pinname="Input String" visible="0" slicecount="1" encoded="0" values="SHOTS">
   </PIN>
   <PIN pinname="Output String" visible="0">
   </PIN>
   <PIN pinname="Show Grid" slicecount="1" values="1">
   </PIN>
   <PIN pinname="String Type" slicecount="1" values="MultiLine">
   </PIN>
   <PIN pinname="Size" slicecount="1" values="11">
   </PIN>
   </NODE>
   <NODE nodename="IOBox (String)" componentmode="InABox" id="12" systemname="IOBox (String)">
   <BOUNDS type="Node" left="11610" top="15765" width="600" height="270">
   </BOUNDS>
   <BOUNDS type="Box" left="11610" top="15765" width="2160" height="345">
   </BOUNDS>
   <PIN pinname="Input String" visible="0" slicecount="1" encoded="0" values="CALIBRATION">
   </PIN>
   <PIN pinname="Output String" visible="0">
   </PIN>
   <PIN pinname="Show Grid" slicecount="1" values="1">
   </PIN>
   <PIN pinname="String Type" slicecount="1" values="MultiLine">
   </PIN>
   <PIN pinname="Size" slicecount="1" values="11">
   </PIN>
   </NODE>
   <NODE nodename="IOBox (String)" componentmode="InABox" id="11" systemname="IOBox (String)">
   <BOUNDS type="Node" left="11610" top="18225" width="3765" height="270">
   </BOUNDS>
   <BOUNDS type="Box" left="11610" top="18225" width="3765" height="270">
   </BOUNDS>
   <PIN pinname="Input String" visible="0" slicecount="1" encoded="0" values="|I:\AUDIO\Samples\VGEE\VEE Effects\VEE FX 067.wav|">
   </PIN>
   <PIN pinname="Output String" visible="1">
   </PIN>
   <PIN pinname="Show Grid" slicecount="1" values="0">
   </PIN>
   <PIN pinname="String Type" slicecount="1" values="MultiLine">
   </PIN>
   </NODE>
   <NODE nodename="IOBox (String)" componentmode="InABox" id="10" systemname="IOBox (String)">
   <BOUNDS type="Node" left="7380" top="15765" width="600" height="270">
   </BOUNDS>
   <BOUNDS type="Box" left="7380" top="15765" width="1125" height="360">
   </BOUNDS>
   <PIN pinname="Input String" visible="0" slicecount="1" encoded="0" values="FOCUS">
   </PIN>
   <PIN pinname="Output String" visible="0">
   </PIN>
   <PIN pinname="Show Grid" slicecount="1" values="1">
   </PIN>
   <PIN pinname="String Type" slicecount="1" values="MultiLine">
   </PIN>
   <PIN pinname="Size" slicecount="1" values="11">
   </PIN>
   </NODE>
   <NODE nodename="IOBox (String)" componentmode="InABox" id="9" systemname="IOBox (String)">
   <BOUNDS type="Node" left="7365" top="16215" width="3765" height="270">
   </BOUNDS>
   <BOUNDS type="Box" left="7365" top="16215" width="3765" height="270">
   </BOUNDS>
   <PIN pinname="Input String" visible="0" slicecount="1" encoded="0" values="|I:\AUDIO\Samples\VGEE\VEE Effects\VEE FX 076.wav|">
   </PIN>
   <PIN pinname="Output String" visible="1">
   </PIN>
   <PIN pinname="Show Grid" slicecount="1" values="0">
   </PIN>
   <PIN pinname="String Type" slicecount="1" values="MultiLine">
   </PIN>
   </NODE>
   <NODE nodename="IOBox (String)" componentmode="InABox" id="8" systemname="IOBox (String)">
   <BOUNDS type="Node" left="15720" top="16485" width="3765" height="270">
   </BOUNDS>
   <BOUNDS type="Box" left="15720" top="16485" width="3765" height="270">
   </BOUNDS>
   <PIN pinname="Input String" visible="0" slicecount="1" encoded="0" values="|I:\AUDIO\Samples\VGEE\VEE Effects\VEE FX 080.wav|">
   </PIN>
   <PIN pinname="Output String" visible="1">
   </PIN>
   <PIN pinname="Show Grid" slicecount="1" values="0">
   </PIN>
   <PIN pinname="String Type" slicecount="1" values="MultiLine">
   </PIN>
   </NODE>
   <NODE nodename="IOBox (String)" componentmode="InABox" id="7" systemname="IOBox (String)">
   <BOUNDS type="Node" left="15750" top="16785" width="3765" height="270">
   </BOUNDS>
   <BOUNDS type="Box" left="15750" top="16785" width="3765" height="270">
   </BOUNDS>
   <PIN pinname="Input String" visible="0" slicecount="1" encoded="0" values="|I:\AUDIO\Samples\VGEE\VEE Effects\VEE FX 082.wav|">
   </PIN>
   <PIN pinname="Output String" visible="1">
   </PIN>
   <PIN pinname="Show Grid" slicecount="1" values="0">
   </PIN>
   <PIN pinname="String Type" slicecount="1" values="MultiLine">
   </PIN>
   </NODE>
   <NODE nodename="IOBox (String)" componentmode="InABox" id="6" systemname="IOBox (String)">
   <BOUNDS type="Node" left="11625" top="18585" width="3765" height="270">
   </BOUNDS>
   <BOUNDS type="Box" left="11625" top="18585" width="3765" height="270">
   </BOUNDS>
   <PIN pinname="Input String" visible="0" slicecount="1" encoded="0" values="|I:\AUDIO\Samples\VGEE\VEE Effects\VEE FX 092.wav|">
   </PIN>
   <PIN pinname="Output String" visible="1">
   </PIN>
   <PIN pinname="Show Grid" slicecount="1" values="0">
   </PIN>
   <PIN pinname="String Type" slicecount="1" values="MultiLine">
   </PIN>
   </NODE>
   <NODE nodename="IOBox (String)" componentmode="InABox" id="5" systemname="IOBox (String)">
   <BOUNDS type="Node" left="15765" top="17130" width="3765" height="270">
   </BOUNDS>
   <BOUNDS type="Box" left="15765" top="17130" width="3765" height="270">
   </BOUNDS>
   <PIN pinname="Input String" visible="0" slicecount="1" encoded="0" values="|I:\AUDIO\Samples\VGEE\VEE Effects\VEE FX 094.wav|">
   </PIN>
   <PIN pinname="Output String" visible="1">
   </PIN>
   <PIN pinname="Show Grid" slicecount="1" values="0">
   </PIN>
   <PIN pinname="String Type" slicecount="1" values="MultiLine">
   </PIN>
   </NODE>
   <NODE nodename="IOBox (String)" componentmode="InABox" id="4" systemname="IOBox (String)">
   <BOUNDS type="Node" left="15810" top="17490" width="3765" height="270">
   </BOUNDS>
   <BOUNDS type="Box" left="15810" top="17490" width="3765" height="270">
   </BOUNDS>
   <PIN pinname="Input String" visible="0" slicecount="1" encoded="0" values="|I:\AUDIO\Samples\VGEE\VEE Effects\VEE FX 096.wav|">
   </PIN>
   <PIN pinname="Output String" visible="1">
   </PIN>
   <PIN pinname="Show Grid" slicecount="1" values="0">
   </PIN>
   <PIN pinname="String Type" slicecount="1" values="MultiLine">
   </PIN>
   </NODE>
   <NODE nodename="IOBox (String)" componentmode="InABox" id="3" systemname="IOBox (String)">
   <BOUNDS type="Node" left="15795" top="17910" width="3765" height="270">
   </BOUNDS>
   <BOUNDS type="Box" left="15795" top="17910" width="4095" height="300">
   </BOUNDS>
   <PIN pinname="Input String" visible="0" slicecount="1" encoded="0" values="|I:\AUDIO\Samples\VGEE\VEE Effects\VEE FX 108.wav **|">
   </PIN>
   <PIN pinname="Output String" visible="1">
   </PIN>
   <PIN pinname="Show Grid" slicecount="1" values="0">
   </PIN>
   <PIN pinname="String Type" slicecount="1" values="MultiLine">
   </PIN>
   </NODE>
   <NODE nodename="IOBox (String)" componentmode="InABox" id="2" systemname="IOBox (String)">
   <BOUNDS type="Node" left="11625" top="18930" width="3930" height="270">
   </BOUNDS>
   <BOUNDS type="Box" left="11625" top="18930" width="3930" height="270">
   </BOUNDS>
   <PIN pinname="Input String" visible="0" slicecount="1" encoded="0" values="|I:\AUDIO\Samples\VGEE\VEE Effects\VEE FX 110.wav **|">
   </PIN>
   <PIN pinname="Output String" visible="1">
   </PIN>
   <PIN pinname="Show Grid" slicecount="1" values="0">
   </PIN>
   <PIN pinname="String Type" slicecount="1" values="MultiLine">
   </PIN>
   </NODE>
   <NODE nodename="IOBox (String)" componentmode="InABox" id="1" systemname="IOBox (String)">
   <BOUNDS type="Node" left="11670" top="19290" width="3930" height="270">
   </BOUNDS>
   <BOUNDS type="Box" left="11670" top="19290" width="3930" height="270">
   </BOUNDS>
   <PIN pinname="Input String" visible="0" slicecount="1" encoded="0" values="|I:\AUDIO\Samples\VGEE\VEE Effects\VEE FX 111.wav **|">
   </PIN>
   <PIN pinname="Output String" visible="1">
   </PIN>
   <PIN pinname="Show Grid" slicecount="1" values="0">
   </PIN>
   <PIN pinname="String Type" slicecount="1" values="MultiLine">
   </PIN>
   </NODE>
   <NODE nodename="IOBox (String)" componentmode="InABox" id="0" systemname="IOBox (String)">
   <BOUNDS type="Node" left="7380" top="16515" width="3765" height="270">
   </BOUNDS>
   <BOUNDS type="Box" left="7380" top="16515" width="3765" height="270">
   </BOUNDS>
   <PIN pinname="Input String" visible="0" slicecount="1" encoded="0" values="|I:\AUDIO\Samples\VGEE\VEE Effects\VEE FX 114.wav|">
   </PIN>
   <PIN pinname="Output String" visible="1">
   </PIN>
   <PIN pinname="Show Grid" slicecount="1" values="0">
   </PIN>
   <PIN pinname="String Type" slicecount="1" values="MultiLine">
   </PIN>
   </NODE>
   <NODE systemname="FFT (DShow9)" nodename="FFT (DShow9)" componentmode="Hidden" id="35">
   <BOUNDS type="Node" left="4530" top="16740" width="100" height="100">
   </BOUNDS>
   <PIN pinname="Audio" visible="1" slicecount="1" values="||">
   </PIN>
   </NODE>
   <NODE nodename="IOBox (String)" componentmode="InABox" id="42" systemname="IOBox (String)">
   <BOUNDS type="Node" left="11295" top="9360" width="3765" height="270">
   </BOUNDS>
   <BOUNDS type="Box" left="11295" top="9360" width="3765" height="270">
   </BOUNDS>
   <PIN pinname="Input String" visible="0" slicecount="1" encoded="0" values="|I:\AUDIO\Samples\VGEE\VEE Effects\VEE FX 064.wav|">
   </PIN>
   <PIN pinname="Output String" visible="1">
   </PIN>
   <PIN pinname="Show Grid" slicecount="1" values="0">
   </PIN>
   <PIN pinname="String Type" slicecount="1" values="MultiLine">
   </PIN>
   </NODE>
   <NODE nodename="IOBox (String)" componentmode="InABox" id="41" systemname="IOBox (String)">
   <BOUNDS type="Node" left="11310" top="9690" width="3765" height="270">
   </BOUNDS>
   <BOUNDS type="Box" left="11310" top="9690" width="3765" height="270">
   </BOUNDS>
   <PIN pinname="Input String" visible="0" slicecount="1" encoded="0" values="|I:\AUDIO\Samples\VGEE\VEE Effects\VEE FX 080.wav|">
   </PIN>
   <PIN pinname="Output String" visible="1">
   </PIN>
   <PIN pinname="Show Grid" slicecount="1" values="0">
   </PIN>
   <PIN pinname="String Type" slicecount="1" values="MultiLine">
   </PIN>
   </NODE>
   <NODE nodename="IOBox (String)" componentmode="InABox" id="40" systemname="IOBox (String)">
   <BOUNDS type="Node" left="11340" top="9990" width="3765" height="270">
   </BOUNDS>
   <BOUNDS type="Box" left="11340" top="9990" width="3765" height="270">
   </BOUNDS>
   <PIN pinname="Input String" visible="0" slicecount="1" encoded="0" values="|I:\AUDIO\Samples\VGEE\VEE Effects\VEE FX 082.wav|">
   </PIN>
   <PIN pinname="Output String" visible="1">
   </PIN>
   <PIN pinname="Show Grid" slicecount="1" values="0">
   </PIN>
   <PIN pinname="String Type" slicecount="1" values="MultiLine">
   </PIN>
   </NODE>
   <NODE nodename="IOBox (String)" componentmode="InABox" id="39" systemname="IOBox (String)">
   <BOUNDS type="Node" left="11355" top="10335" width="3765" height="270">
   </BOUNDS>
   <BOUNDS type="Box" left="11355" top="10335" width="3765" height="270">
   </BOUNDS>
   <PIN pinname="Input String" visible="0" slicecount="1" encoded="0" values="|I:\AUDIO\Samples\VGEE\VEE Effects\VEE FX 094.wav|">
   </PIN>
   <PIN pinname="Output String" visible="1">
   </PIN>
   <PIN pinname="Show Grid" slicecount="1" values="0">
   </PIN>
   <PIN pinname="String Type" slicecount="1" values="MultiLine">
   </PIN>
   </NODE>
   <NODE nodename="IOBox (String)" componentmode="InABox" id="38" systemname="IOBox (String)">
   <BOUNDS type="Node" left="11400" top="10695" width="3765" height="270">
   </BOUNDS>
   <BOUNDS type="Box" left="11400" top="10695" width="3765" height="270">
   </BOUNDS>
   <PIN pinname="Input String" visible="0" slicecount="1" encoded="0" values="|I:\AUDIO\Samples\VGEE\VEE Effects\VEE FX 096.wav|">
   </PIN>
   <PIN pinname="Output String" visible="1">
   </PIN>
   <PIN pinname="Show Grid" slicecount="1" values="0">
   </PIN>
   <PIN pinname="String Type" slicecount="1" values="MultiLine">
   </PIN>
   </NODE>
   <NODE nodename="IOBox (String)" componentmode="InABox" id="37" systemname="IOBox (String)">
   <BOUNDS type="Node" left="11865" top="11130" width="3765" height="270">
   </BOUNDS>
   <BOUNDS type="Box" left="11865" top="11130" width="4920" height="1335">
   </BOUNDS>
   <PIN pinname="Input String" visible="0" slicecount="4" encoded="0" values="..\..\..\Assets\Sound\idle2.wav,|I:\AUDIO\Samples\VGEE\VEE Effects\VEE FX 108.wav|,,">
   </PIN>
   <PIN pinname="Output String" visible="1">
   </PIN>
   <PIN pinname="Show Grid" slicecount="1" values="0">
   </PIN>
   <PIN pinname="String Type" slicecount="1" values="Filename">
   </PIN>
   <PIN pinname="Rows" slicecount="1" values="4">
   </PIN>
   <PIN pinname="SliceCount Mode" slicecount="1" values="ColsRowsPages">
   </PIN>
   </NODE>
   <LINK srcnodeid="37" srcpinname="Output String" dstnodeid="32" dstpinname="Input String">
   </LINK>
   <NODE systemname="GetSlice (String)" nodename="GetSlice (String)" componentmode="Hidden" id="43">
   <BOUNDS type="Node" left="11535" top="13770" width="100" height="100">
   </BOUNDS>
   <PIN pinname="Input" visible="1" slicecount="1" encoded="0" values="text">
   </PIN>
   <PIN pinname="Output" visible="1">
   </PIN>
   <PIN pinname="Index" visible="1" slicecount="1" values="0">
   </PIN>
   </NODE>
   <LINK srcnodeid="32" srcpinname="Output String" dstnodeid="43" dstpinname="Input">
   </LINK>
   <NODE nodename="IOBox (Value Advanced)" componentmode="InABox" id="50" systemname="IOBox (Value Advanced)">
   <BOUNDS type="Node" left="16005" top="14160" width="0" height="0">
   </BOUNDS>
   <BOUNDS type="Box" left="16005" top="14160" width="795" height="240">
   </BOUNDS>
   <PIN pinname="Y Input Value" slicecount="1" values="1">
   </PIN>
   <PIN pinname="Units" slicecount="1" encoded="0" values="||">
   </PIN>
   <PIN pinname="Precision" slicecount="1" values="4">
   </PIN>
   <PIN pinname="Value Type" slicecount="1" values="Integer">
   </PIN>
   </NODE>
   <LINK srcnodeid="50" srcpinname="Y Output Value" dstnodeid="43" dstpinname="Index">
   </LINK>
   <NODE nodename="IOBox (String)" componentmode="InABox" id="51" systemname="IOBox (String)">
   <BOUNDS type="Node" left="3690" top="19710" width="5670" height="270">
   </BOUNDS>
   <BOUNDS type="Box" left="3690" top="19710" width="5670" height="270">
   </BOUNDS>
   <PIN pinname="Input String" visible="0" slicecount="1" encoded="0" values="C:\Users\julian\Dropbox\__FH\Bachelor\Entwicklung\Assets\Sound\idle2.wav">
   </PIN>
   <PIN pinname="Output String" visible="0">
   </PIN>
   <PIN pinname="Show Grid" slicecount="1" values="0">
   </PIN>
   <PIN pinname="String Type" slicecount="1" values="MultiLine">
   </PIN>
   </NODE>
   <NODE nodename="IOBox (String)" componentmode="InABox" id="52" systemname="IOBox (String)" exposed="0">
   <BOUNDS type="Node" left="5010" top="12660" width="3765" height="270">
   </BOUNDS>
   <BOUNDS type="Box" left="5010" top="12660" width="5580" height="570">
   </BOUNDS>
   <PIN pinname="Input String" visible="0" slicecount="2" encoded="0" values="|I:\AUDIO\Samples\VGEE\VEE Effects\VEE FX 048.wav|,|I:\AUDIO\Samples\VGEE\VEE Effects\VEE FX 064.wav|">
   </PIN>
   <PIN pinname="Output String" visible="1">
   </PIN>
   <PIN pinname="Show Grid" slicecount="1" values="0">
   </PIN>
   <PIN pinname="String Type" slicecount="1" values="MultiLine">
   </PIN>
   <PIN pinname="Rows" slicecount="1" values="2">
   </PIN>
   <PIN pinname="SliceCount Mode" slicecount="1" values="ColsRowsPages">
   </PIN>
   </NODE>
   <NODE systemname="IOBox (Value Advanced)" nodename="IOBox (Value Advanced)" componentmode="InABox" id="95">
   <BOUNDS type="Node" left="1260" top="870" width="100" height="100">
   </BOUNDS>
   <BOUNDS type="Box" left="1260" top="870" width="480" height="480">
   </BOUNDS>
   <PIN pinname="Value Type" slicecount="1" values="Boolean">
   </PIN>
   <PIN pinname="Behavior" slicecount="1" values="Toggle">
   </PIN>
   <PIN pinname="Descriptive Name" slicecount="1" encoded="0" values="Target">
   </PIN>
   <PIN pinname="Y Output Value" visible="1">
   </PIN>
   </NODE>
   <NODE systemname="TogEdge (Animation)" nodename="TogEdge (Animation)" componentmode="Hidden" id="96">
   <BOUNDS type="Node" left="1260" top="1755" width="100" height="100">
   </BOUNDS>
   <PIN pinname="Input" visible="1">
   </PIN>
   <PIN pinname="Up Edge" visible="1">
   </PIN>
   <PIN pinname="Down Edge" visible="1">
   </PIN>
   </NODE>
   <LINK srcnodeid="95" srcpinname="Y Output Value" dstnodeid="96" dstpinname="Input">
   </LINK>
   <NODE systemname="IOBox (Value Advanced)" nodename="IOBox (Value Advanced)" componentmode="InABox" id="97">
   <BOUNDS type="Node" left="2265" top="870" width="100" height="100">
   </BOUNDS>
   <BOUNDS type="Box" left="2265" top="870" width="480" height="480">
   </BOUNDS>
   <PIN pinname="Value Type" slicecount="1" values="Boolean">
   </PIN>
   <PIN pinname="Behavior" slicecount="1" values="Bang">
   </PIN>
   <PIN pinname="Descriptive Name" slicecount="1" encoded="0" values="Shoot">
   </PIN>
   <PIN pinname="Y Output Value" visible="1">
   </PIN>
   </NODE>
   <NODE nodename="IOBox (String)" componentmode="InABox" id="107" systemname="IOBox (String)">
   <BOUNDS type="Node" left="5010" top="13500" width="3765" height="270">
   </BOUNDS>
   <BOUNDS type="Box" left="5010" top="13500" width="3765" height="270">
   </BOUNDS>
   <PIN pinname="Input String" visible="0" slicecount="1" values="|I:\AUDIO\Samples\VGEE\VEE Effects\VEE FX 048.wav|">
   </PIN>
   <PIN pinname="Output String" visible="1">
   </PIN>
   <PIN pinname="Show Grid" slicecount="1" values="0">
   </PIN>
   <PIN pinname="String Type" slicecount="1" values="MultiLine">
   </PIN>
   </NODE>
   <NODE systemname="FlipFlop (Animation)" nodename="FlipFlop (Animation)" componentmode="Hidden" id="109">
   <BOUNDS type="Node" left="5958" top="4095" width="100" height="100">
   </BOUNDS>
   <PIN pinname="Set" slicecount="1" visible="1" values="0">
   </PIN>
   <PIN pinname="Reset" visible="1">
   </PIN>
   <PIN pinname="Output" visible="1">
   </PIN>
   <PIN pinname="Inverse Output" visible="1">
   </PIN>
   </NODE>
   <NODE systemname="Damper (Animation)" nodename="Damper (Animation)" componentmode="Hidden" id="112">
   <BOUNDS type="Node" left="6570" top="6645" width="100" height="100">
   </BOUNDS>
   <PIN pinname="Go To Position" visible="1">
   </PIN>
   <PIN pinname="Position Out" visible="1">
   </PIN>
   </NODE>
   <NODE systemname="GetSlice (String)" nodename="GetSlice (String)" componentmode="Hidden" id="115">
   <BOUNDS type="Node" left="13170" top="6645" width="100" height="100">
   </BOUNDS>
   <PIN pinname="Input" visible="1">
   </PIN>
   <PIN pinname="Output" visible="1">
   </PIN>
   <PIN pinname="Index" visible="1">
   </PIN>
   </NODE>
   <NODE systemname="FlipFlop (Animation)" nodename="FlipFlop (Animation)" componentmode="Hidden" id="121">
   <BOUNDS type="Node" left="1290" top="4125" width="100" height="100">
   </BOUNDS>
   <PIN pinname="Set" slicecount="1" visible="1" values="0">
   </PIN>
   <PIN pinname="Reset" visible="1" slicecount="1" values="0">
   </PIN>
   <PIN pinname="Output" visible="1">
   </PIN>
   <PIN pinname="Inverse Output" visible="1">
   </PIN>
   </NODE>
   <LINK srcnodeid="121" srcpinname="Output" dstnodeid="115" dstpinname="Index" linkstyle="Bezier">
   <LINKPOINT x="1350" y="5505">
   </LINKPOINT>
   <LINKPOINT x="13785" y="5505">
   </LINKPOINT>
   </LINK>
   <LINK srcnodeid="96" srcpinname="Up Edge" dstnodeid="121" dstpinname="Reset">
   </LINK>
   <NODE systemname="OR (Boolean)" nodename="OR (Boolean)" componentmode="Hidden" id="124">
   <BOUNDS type="Node" left="1251" top="6750" width="100" height="100">
   </BOUNDS>
   <PIN pinname="Input 1" visible="1">
   </PIN>
   <PIN pinname="Input 2" visible="1">
   </PIN>
   <PIN pinname="Output" visible="1">
   </PIN>
   </NODE>
   <LINK srcnodeid="96" srcpinname="Down Edge" dstnodeid="109" dstpinname="Set" linkstyle="Bezier">
   <LINKPOINT x="1530" y="3215">
   </LINKPOINT>
   <LINKPOINT x="6405" y="2875">
   </LINKPOINT>
   </LINK>
   <LINK srcnodeid="96" srcpinname="Up Edge" dstnodeid="109" dstpinname="Reset" linkstyle="Bezier">
   <LINKPOINT x="870" y="3215">
   </LINKPOINT>
   <LINKPOINT x="7005" y="2875">
   </LINKPOINT>
   </LINK>
   <LINK srcnodeid="96" srcpinname="Up Edge" dstnodeid="124" dstpinname="Input 1">
   </LINK>
   <LINK srcnodeid="109" srcpinname="Inverse Output" dstnodeid="112" dstpinname="Go To Position">
   </LINK>
   <NODE nodename="IOBox (Value Advanced)" componentmode="InABox" id="129" systemname="IOBox (Value Advanced)">
   <BOUNDS type="Node" left="9225" top="6645" width="0" height="0">
   </BOUNDS>
   <BOUNDS type="Box" left="9225" top="6645" width="795" height="240">
   </BOUNDS>
   <PIN pinname="Y Input Value" slicecount="1" values="12.5">
   </PIN>
   <PIN pinname="Units" slicecount="1" values="||">
   </PIN>
   <PIN pinname="Precision" slicecount="1" values="4">
   </PIN>
   </NODE>
   <NODE nodename="IOBox (Value Advanced)" componentmode="InABox" id="130" systemname="IOBox (Value Advanced)">
   <BOUNDS type="Node" left="9870" top="6939" width="0" height="0">
   </BOUNDS>
   <BOUNDS type="Box" left="9870" top="6939" width="795" height="240">
   </BOUNDS>
   <PIN pinname="Y Input Value" slicecount="1" values="14">
   </PIN>
   <PIN pinname="Units" slicecount="1" values="||">
   </PIN>
   <PIN pinname="Precision" slicecount="1" values="4">
   </PIN>
   </NODE>
   <NODE id="131" nodename="IOBox (Value Advanced)" componentmode="InABox" systemname="IOBox (Value Advanced)">
   <PIN pinname="Y Output Value" visible="1">
   </PIN>
   <BOUNDS type="Node" left="3480" top="5355" width="0" height="0">
   </BOUNDS>
   <BOUNDS type="Box" left="3480" top="5355" width="795" height="240">
   </BOUNDS>
   <PIN pinname="Y Input Value" slicecount="1" values="5.5">
   </PIN>
   <PIN pinname="Units" slicecount="1" values="||">
   </PIN>
   <PIN pinname="Precision" slicecount="1" values="4">
   </PIN>
   </NODE>
   <NODE id="132" systemname="Multiply (Value)" nodename="Multiply (Value)" componentmode="Hidden">
   <PIN pinname="Output" visible="1">
   </PIN>
   <PIN pinname="Input 1" visible="1" slicecount="1" values="0">
   </PIN>
   <PIN pinname="Input 2" visible="1">
   </PIN>
   <BOUNDS type="Node" left="3225" top="6660" width="100" height="100">
   </BOUNDS>
   </NODE>
   <LINK srcnodeid="131" srcpinname="Y Output Value" dstnodeid="132" dstpinname="Input 2">
   <LINKPOINT x="3750" y="6105">
   </LINKPOINT>
   </LINK>
   <NODE id="126" nodename="IOBox (Value Advanced)" componentmode="InABox" systemname="IOBox (Value Advanced)">
   <PIN pinname="Y Input Value">
   </PIN>
   <BOUNDS type="Node" left="3225" top="4710" width="0" height="0">
   </BOUNDS>
   <BOUNDS type="Box" left="3225" top="4710" width="795" height="240">
   </BOUNDS>
   <PIN pinname="Units" slicecount="1" values="s">
   </PIN>
   <PIN pinname="Precision" slicecount="1" values="4">
   </PIN>
   <PIN pinname="Y Output Value" visible="1">
   </PIN>
   </NODE>
   <NODE id="125" systemname="Stopwatch (Animation)" nodename="Stopwatch (Animation)" componentmode="Hidden">
   <PIN pinname="Run" visible="1">
   </PIN>
   <PIN pinname="Reset" visible="1">
   </PIN>
   <BOUNDS type="Node" left="3225" top="4200" width="100" height="100">
   </BOUNDS>
   </NODE>
   <LINK srcnodeid="125" srcpinname="Output" dstnodeid="126" dstpinname="Y Input Value">
   </LINK>
   <LINK srcnodeid="96" srcpinname="Up Edge" dstnodeid="125" dstpinname="Reset" linkstyle="Bezier">
   <LINKPOINT x="1320" y="3098">
   </LINKPOINT>
   <LINKPOINT x="3960" y="3098">
   </LINKPOINT>
   </LINK>
   <LINK srcnodeid="95" srcpinname="Y Output Value" dstnodeid="125" dstpinname="Run" linkstyle="Bezier">
   <LINKPOINT x="1320" y="2768">
   </LINKPOINT>
   <LINKPOINT x="3225" y="2768">
   </LINKPOINT>
   </LINK>
   <NODE systemname="R (String)" nodename="R (String)" componentmode="Hidden" id="135">
   <BOUNDS type="Node" left="13320" top="2820" width="100" height="100">
   </BOUNDS>
   <PIN pinname="Receive String" slicecount="1" visible="1" values="|System Path|">
   </PIN>
   <PIN pinname="Input Value" visible="1">
   </PIN>
   </NODE>
   <NODE systemname="Add (String)" nodename="Add (String)" componentmode="Hidden" id="136">
   <BOUNDS type="Node" left="13335" top="3240" width="100" height="100">
   </BOUNDS>
   <PIN pinname="Input 2" slicecount="1" values="Sound\">
   </PIN>
   <PIN pinname="Input 1" visible="1">
   </PIN>
   <PIN pinname="Output" visible="1">
   </PIN>
   </NODE>
   <LINK srcnodeid="135" srcpinname="Input Value" dstnodeid="136" dstpinname="Input 1">
   </LINK>
   <NODE systemname="Dir (File)" nodename="Dir (File)" componentmode="Hidden" id="137">
   <BOUNDS type="Node" left="13185" top="4755" width="100" height="100">
   </BOUNDS>
   <PIN pinname="Directory" visible="1">
   </PIN>
   <PIN pinname="Update" slicecount="1" values="0">
   </PIN>
   <PIN pinname="Filenames" visible="1">
   </PIN>
   <PIN pinname="Include Hidden" slicecount="1" values="0">
   </PIN>
   </NODE>
   <NODE id="127" systemname="LT (Value)" nodename="LT (Value)" componentmode="Hidden">
   <PIN pinname="Input 2" visible="1">
   </PIN>
   <PIN pinname="Output" visible="1">
   </PIN>
   <PIN pinname="Input 1" visible="1">
   </PIN>
   <BOUNDS type="Node" left="3225" top="5775" width="100" height="100">
   </BOUNDS>
   </NODE>
   <LINK srcnodeid="131" srcpinname="Y Output Value" dstnodeid="127" dstpinname="Input 2">
   </LINK>
   <LINK srcnodeid="127" srcpinname="Output" dstnodeid="132" dstpinname="Input 1">
   </LINK>
   <LINK srcnodeid="126" srcpinname="Y Output Value" dstnodeid="127" dstpinname="Input 1" linkstyle="PolyLine">
   </LINK>
   <NODE systemname="Add (String)" nodename="Add (String)" componentmode="Hidden" id="153">
   <BOUNDS type="Node" left="13350" top="4200" width="100" height="100">
   </BOUNDS>
   <PIN pinname="Input 1" visible="1">
   </PIN>
   <PIN pinname="Input 2" slicecount="1" values="\shoot">
   </PIN>
   <PIN pinname="Output" visible="1">
   </PIN>
   </NODE>
   <LINK srcnodeid="136" srcpinname="Output" dstnodeid="153" dstpinname="Input 1">
   </LINK>
   <NODE nodename="IOBox (String)" componentmode="InABox" id="154" systemname="IOBox (String)">
   <BOUNDS type="Node" left="13530" top="3555" width="0" height="0">
   </BOUNDS>
   <BOUNDS type="Box" left="13530" top="3555" width="825" height="525">
   </BOUNDS>
   <PIN pinname="Input String" slicecount="2" values="target\,shoot\">
   </PIN>
   <PIN pinname="Default" slicecount="1" values="text">
   </PIN>
   <PIN pinname="File Mask" slicecount="1" values="||">
   </PIN>
   <PIN pinname="Maximum Characters" slicecount="1" values="-1">
   </PIN>
   <PIN pinname="Rows" slicecount="1" values="2">
   </PIN>
   <PIN pinname="SliceCount Mode" slicecount="1" values="ColsRowsPages">
   </PIN>
   </NODE>
   <LINK srcnodeid="154" srcpinname="Output String" dstnodeid="153" dstpinname="Input 2">
   </LINK>
   <LINK srcnodeid="153" srcpinname="Output" dstnodeid="137" dstpinname="Directory">
   </LINK>
   <NODE systemname="TogEdge (Animation)" nodename="TogEdge (Animation)" componentmode="Hidden" id="156">
   <BOUNDS type="Node" left="2265" top="1755" width="100" height="100">
   </BOUNDS>
   <PIN pinname="Input" visible="1">
   </PIN>
   <PIN pinname="Up Edge" visible="1">
   </PIN>
   </NODE>
   <LINK srcnodeid="97" srcpinname="Y Output Value" dstnodeid="156" dstpinname="Input">
   </LINK>
   <LINK srcnodeid="156" srcpinname="Up Edge" dstnodeid="121" dstpinname="Set">
   </LINK>
   <LINK srcnodeid="156" srcpinname="Up Edge" dstnodeid="124" dstpinname="Input 2">
   </LINK>
   <NODE systemname="FileStream (Irrklang)" filename="%VVVV%\addonpack\lib\nodes\plugins\Irrklang2.dll" nodename="FileStream (Irrklang)" componentmode="Hidden" id="84">
   <BOUNDS type="Node" left="1245" top="8730" width="12000" height="270">
   </BOUNDS>
   <PIN pinname="File Name" visible="1">
   </PIN>
   <PIN pinname="Seek Time" visible="1">
   </PIN>
   <PIN pinname="Do Seek" visible="1">
   </PIN>
   <PIN pinname="Play" visible="1">
   </PIN>
   <PIN pinname="Handle Out" visible="1">
   </PIN>
   <PIN pinname="Pitch">
   </PIN>
   <PIN pinname="Filename" visible="1">
   </PIN>
   <PIN pinname="Device" slicecount="1" values="|DigitalOutput-1 (NVIDIA High Definition Audio)|">
   </PIN>
   <PIN pinname="Play Mode" slicecount="1" values="2D">
   </PIN>
   <PIN pinname="Stop" slicecount="1" visible="1" values="0">
   </PIN>
   <PIN pinname="Volume" visible="1" slicecount="1" values="1">
   </PIN>
   <PIN pinname="Pause" slicecount="1" values="0">
   </PIN>
   <PIN pinname="Loop" visible="1">
   </PIN>
   <PIN pinname="Maximal Distance">
   </PIN>
   <PIN pinname="Speed" visible="1" slicecount="1" values="1">
   </PIN>
   </NODE>
   <LINK srcnodeid="124" srcpinname="Output" dstnodeid="84" dstpinname="Play" linkstyle="PolyLine">
   </LINK>
   <LINK srcnodeid="129" srcpinname="Y Output Value" dstnodeid="84" dstpinname="Minimal Distance">
   </LINK>
   <LINK srcnodeid="130" srcpinname="Y Output Value" dstnodeid="84" dstpinname="Maximal Distance">
   </LINK>
   <LINK srcnodeid="124" srcpinname="Output" dstnodeid="84" dstpinname="Do Seek">
   </LINK>
   <LINK srcnodeid="132" srcpinname="Output" dstnodeid="84" dstpinname="Seek Time">
   </LINK>
   <LINK srcnodeid="115" srcpinname="Output" dstnodeid="84" dstpinname="Filename">
   </LINK>
   <LINK srcnodeid="121" srcpinname="Inverse Output" dstnodeid="84" dstpinname="Loop">
   </LINK>
   <LINK srcnodeid="137" srcpinname="Filenames" dstnodeid="115" dstpinname="Input">
   </LINK>
   <NODE systemname="String2Enum (Enumerations)" nodename="String2Enum (Enumerations)" componentmode="Hidden" id="159">
   <BOUNDS type="Node" left="13320" top="2370" width="100" height="100">
   </BOUNDS>
   <PIN pinname="Enum" visible="1">
   </PIN>
   </NODE>
   <NODE nodename="IOBox (String)" componentmode="InABox" id="160" systemname="IOBox (String)">
   <BOUNDS type="Node" left="13305" top="1995" width="0" height="0">
   </BOUNDS>
   <BOUNDS type="Box" left="13305" top="1995" width="1050" height="240">
   </BOUNDS>
   <PIN pinname="Input String" slicecount="1" values="|Path to Assets|">
   </PIN>
   <PIN pinname="Default" slicecount="1" values="(nil)">
   </PIN>
   <PIN pinname="File Mask" slicecount="1" values="||">
   </PIN>
   <PIN pinname="Maximum Characters" slicecount="1" values="-1">
   </PIN>
   </NODE>
   <LINK srcnodeid="160" srcpinname="Output String" dstnodeid="159" dstpinname="String Value">
   </LINK>
   <LINK srcnodeid="159" srcpinname="Enum" dstnodeid="135" dstpinname="Receive String">
   </LINK>
   <NODE systemname="MonoFlop (Animation)" nodename="MonoFlop (Animation)" componentmode="Hidden" id="161">
   <BOUNDS type="Node" left="7410" top="6660" width="100" height="100">
   </BOUNDS>
   <PIN pinname="Set" visible="1">
   </PIN>
   <PIN pinname="Output" visible="1">
   </PIN>
   <PIN pinname="Time" slicecount="1" values="2">
   </PIN>
   </NODE>
   <LINK srcnodeid="97" srcpinname="Y Output Value" dstnodeid="161" dstpinname="Set">
   </LINK>
   <NODE systemname="OR (Boolean)" nodename="OR (Boolean)" componentmode="Hidden" id="162">
   <BOUNDS type="Node" left="6570" top="7230" width="100" height="100">
   </BOUNDS>
   <PIN pinname="Input 1" visible="1">
   </PIN>
   <PIN pinname="Input 2" visible="1">
   </PIN>
   <PIN pinname="Output" visible="1">
   </PIN>
   </NODE>
   <LINK srcnodeid="112" srcpinname="Position Out" dstnodeid="162" dstpinname="Input 1">
   </LINK>
   <LINK srcnodeid="161" srcpinname="Output" dstnodeid="162" dstpinname="Input 2">
   </LINK>
   <LINK srcnodeid="162" srcpinname="Output" dstnodeid="84" dstpinname="Volume">
   </LINK>
   </PATCH>